MANIFEST.in
README.md
setup.cfg
setup.py
etsy/__init__.py
etsy/_core.py
etsy/_multipartformdataencode.py
etsy/_v2.py
etsy/etsy_env.py
etsy/exceptions.py
etsy/oauth.py
etsy/request_oauth.py
etsy/test_v2.py
pyetsy.egg-info/PKG-INFO
pyetsy.egg-info/SOURCES.txt
pyetsy.egg-info/dependency_links.txt
pyetsy.egg-info/requires.txt
pyetsy.egg-info/top_level.txt
test/test_core.py