Metadata-Version: 1.0
Name: pyetsy
Version: 0.5.0
Summary: Python access to the Etsy API
Home-page: UNKNOWN
Author: Dan McKinley & Fulfil.IO Inc.
Author-email: dan@etsy.com,support@fulfil.io
License: GPL v3
Keywords: etsy api handmade
Platform: UNKNOWN
